ytree/__init__.py
ytree/config.py
ytree/analysis/__init__.py
ytree/analysis/analysis_operators.py
ytree/analysis/analysis_pipeline.py
ytree/data_structures/__init__.py
ytree/data_structures/arbor.py
ytree/data_structures/detection.py
ytree/data_structures/fields.py
ytree/data_structures/io.py
ytree/data_structures/load.py
ytree/data_structures/node_container.py
ytree/data_structures/node_link.py
ytree/data_structures/save_arbor.py
ytree/data_structures/tree_node.py
ytree/data_structures/tree_node_selector.py
ytree/frontends/__init__.py
ytree/frontends/api.py
ytree/frontends/ahf/__init__.py
ytree/frontends/ahf/arbor.py
ytree/frontends/ahf/fields.py
ytree/frontends/ahf/io.py
ytree/frontends/ahf/misc.py
ytree/frontends/consistent_trees/__init__.py
ytree/frontends/consistent_trees/arbor.py
ytree/frontends/consistent_trees/fields.py
ytree/frontends/consistent_trees/io.py
ytree/frontends/consistent_trees/utilities.py
ytree/frontends/consistent_trees_hdf5/__init__.py
ytree/frontends/consistent_trees_hdf5/arbor.py
ytree/frontends/consistent_trees_hdf5/fields.py
ytree/frontends/consistent_trees_hdf5/io.py
ytree/frontends/csv/__init__.py
ytree/frontends/csv/arbor.py
ytree/frontends/csv/io.py
ytree/frontends/gadget4/__init__.py
ytree/frontends/gadget4/arbor.py
ytree/frontends/gadget4/fields.py
ytree/frontends/gadget4/io.py
ytree/frontends/lhalotree/__init__.py
ytree/frontends/lhalotree/arbor.py
ytree/frontends/lhalotree/fields.py
ytree/frontends/lhalotree/io.py
ytree/frontends/lhalotree/utils.py
ytree/frontends/lhalotree_hdf5/__init__.py
ytree/frontends/lhalotree_hdf5/arbor.py
ytree/frontends/lhalotree_hdf5/fields.py
ytree/frontends/lhalotree_hdf5/io.py
ytree/frontends/moria/__init__.py
ytree/frontends/moria/arbor.py
ytree/frontends/moria/fields.py
ytree/frontends/moria/io.py
ytree/frontends/rockstar/__init__.py
ytree/frontends/rockstar/arbor.py
ytree/frontends/rockstar/fields.py
ytree/frontends/rockstar/io.py
ytree/frontends/rockstar/misc.py
ytree-3.3.1.dist-info/licenses/LICENSE
ytree-3.3.1.dist-info/METADATA
ytree-3.3.1.dist-info/WHEEL
ytree-3.3.1.dist-info/top_level.txt
ytree-3.3.1.dist-info/RECORD
