Metadata-Version: 2.4
Name: ytree
Version: 3.3.1
Summary: A Python package for analyzing tree data and especially merger trees.
Author-email: Britton Smith <brittonsmith@gmail.com>
Project-URL: Homepage, https://github.com/ytree-project/ytree
Project-URL: Documentation, https://ytree.readthedocs.io/en/stable/index.html
Project-URL: Changelog, https://ytree.readthedocs.io/en/latest/Changelog.html
Project-URL: Repository, https://github.com/ytree-project/ytree
Project-URL: Issues, https://github.com/ytree-project/ytree/issues
Keywords: python,data,analysis,astronomy,astrophysics,simulations,merger trees,trees
Classifier: Development Status :: 5 - Production/Stable
Classifier: Environment :: Console
Classifier: Intended Audience :: Science/Research
Classifier: Topic :: Scientific/Engineering :: Astronomy
Classifier: License :: OSI Approved :: BSD License
Classifier: Operating System :: MacOS :: MacOS X
Classifier: Operating System :: POSIX :: Linux
Classifier: Operating System :: Unix
Classifier: Natural Language :: English
Classifier: Programming Language :: Python :: 3.9
Classifier: Programming Language :: Python :: 3.10
Classifier: Programming Language :: Python :: 3.11
Classifier: Programming Language :: Python :: 3.12
Requires-Python: >=3.9
License-File: LICENSE
Requires-Dist: configparser
Requires-Dist: h5py
Requires-Dist: more_itertools>=8.4
Requires-Dist: numpy
Requires-Dist: unyt>=3.0.1
Requires-Dist: yt>=4.2
Provides-Extra: parallel
Requires-Dist: mpi4py; extra == "parallel"
Provides-Extra: dev
Requires-Dist: codecov; extra == "dev"
Requires-Dist: pydot; extra == "dev"
Requires-Dist: pytest>=3.6; extra == "dev"
Requires-Dist: pytest-cov; extra == "dev"
Requires-Dist: twine; extra == "dev"
Requires-Dist: wheel; extra == "dev"
Requires-Dist: sphinx; extra == "dev"
Requires-Dist: sphinx_rtd_theme; extra == "dev"
Provides-Extra: rtd
Requires-Dist: codecov; extra == "rtd"
Requires-Dist: pydot; extra == "rtd"
Requires-Dist: pytest>=3.6; extra == "rtd"
Requires-Dist: pytest-cov; extra == "rtd"
Requires-Dist: twine; extra == "rtd"
Requires-Dist: wheel; extra == "rtd"
Requires-Dist: sphinx_rtd_theme; extra == "rtd"
Dynamic: license-file
